usure/__init__.py
usure/core.py
usure/example_sync.py
usure-1.0.0.dist-info/LICENSE.txt
usure-1.0.0.dist-info/METADATA
usure-1.0.0.dist-info/WHEEL
usure-1.0.0.dist-info/top_level.txt
usure-1.0.0.dist-info/RECORD
